{"algorithm":"K-Means","WSSE":3484687.0955893435,"clusters":[{"id":1,"size":5157,"error":129010.87023817012,"terms":["room","burger","would","get","one","good","like","place","time","us"]},{"id":2,"size":5965,"error":137131.54128824963,"terms":["food","place","good","great","time","service","like","get","one","would"]},{"id":3,"size":3528,"error":120391.8579151592,"terms":["like","food","good","one","place","would","get","time","really","us"]},{"id":4,"size":5241,"error":130417.21141347828,"terms":["would","get","back","us","one","time","said","told","like","service"]},{"id":5,"size":1105,"error":241918.05236360437,"terms":["food","good","place","would","get","like","one","service","time","great"]},{"id":6,"size":5739,"error":126487.3648042221,"terms":["hair","would","get","time","like","company","cut","back","one","good"]},{"id":7,"size":4843,"error":131059.98484921193,"terms":["place","food","good","like","breakfast","one","time","would","great","get"]},{"id":8,"size":6251,"error":377962.01620263455,"terms":["one","would","like","get","good","time","food","us","back","place"]},{"id":9,"size":9848,"error":391546.38484582736,"terms":["would","one","like","get","time","us","back","said","told","good"]},{"id":10,"size":3483,"error":104878.3604459475,"terms":["good","place","food","like","great","get","one","time","cheese","would"]},{"id":11,"size":3739,"error":131921.64566883608,"terms":["place","like","food","good","time","one","would","get","back","great"]},{"id":12,"size":27435,"error":493177.83813092235,"terms":["place","food","good","like","one","would","time","get","back","great"]},{"id":13,"size":3915,"error":311219.3502835165,"terms":["place","food","good","time","get","service","one","great","would","like"]},{"id":14,"size":3071,"error":361247.58857128746,"terms":["food","place","time","would","one","like","good","get","us","back"]},{"id":15,"size":8065,"error":186411.19276933582,"terms":["food","good","place","great","service","one","time","like","would","get"]},{"id":16,"size":2615,"error":109905.83579896353,"terms":["car","would","get","back","call","time","service","told","one","like"]}]}